cherrypy_ask_sdk/__init__.py
cherrypy_ask_sdk/ask_sdk_skill_tool.py
cherrypy_ask_sdk-0.1.3.dist-info/LICENSE
cherrypy_ask_sdk-0.1.3.dist-info/METADATA
cherrypy_ask_sdk-0.1.3.dist-info/WHEEL
cherrypy_ask_sdk-0.1.3.dist-info/top_level.txt
cherrypy_ask_sdk-0.1.3.dist-info/RECORD
