Metadata-Version: 2.1
Name: cherrypy-ask-sdk
Version: 0.1.3
Summary: CherryPy ASK SDK - Extending ASK SDK to work with CherryPy
Home-page: https://github.com/cyraxjoe/cherrypy-ask-sdk
Author: Joel Rivera
Author-email: rivera@joel.mx
License: Apache 2.0
Platform: UNKNOWN
Classifier: Development Status :: 4 - Beta
Classifier: Intended Audience :: Developers
Classifier: Natural Language :: English
Classifier: Operating System :: OS Independent
Classifier: Framework :: CherryPy
Classifier: License :: OSI Approved :: Apache Software License
Classifier: Programming Language :: Python
Classifier: Programming Language :: Python :: 2
Classifier: Programming Language :: Python :: 2.7
Classifier: Programming Language :: Python :: 3
Classifier: Programming Language :: Python :: 3.6
Classifier: Programming Language :: Python :: 3.7
Requires-Python: !=3.0.*,!=3.1.*,!=3.2.*,!=3.3.*,!=3.4.*,!=3.5.*,>2.6
Requires-Dist: ask-sdk
Requires-Dist: ask-sdk-webservice-support
Requires-Dist: CherryPy
